easydel/__init__.py
easydel/data/__init__.py
easydel/data/core/__init__.py
easydel/data/core/config.py
easydel/data/core/protocols.py
easydel/data/core/types.py
easydel/data/distributed/__init__.py
easydel/data/distributed/ray_utils.py
easydel/data/execution/__init__.py
easydel/data/execution/cache.py
easydel/data/execution/loader.py
easydel/data/execution/pipeline.py
easydel/data/execution/save.py
easydel/data/sources/__init__.py
easydel/data/sources/base.py
easydel/data/sources/hf_wrapper.py
easydel/data/transforms/__init__.py
easydel/data/transforms/base.py
easydel/data/transforms/chat_template.py
easydel/data/transforms/field_ops.py
easydel/data/transforms/filter_ops.py
easydel/data/transforms/map_ops.py
easydel/data/transforms/mixture.py
easydel/data/transforms/pack.py
easydel/data/transforms/source.py
easydel/data/transforms/tokenize.py
easydel/data/utils.py
easydel/inference/__init__.py
easydel/inference/decoders.py
easydel/inference/esurge/__init__.py
easydel/inference/esurge/config.py
easydel/inference/esurge/core/__init__.py
easydel/inference/esurge/core/binary_search.py
easydel/inference/esurge/core/coordinator.py
easydel/inference/esurge/core/interface.py
easydel/inference/esurge/core/manager.py
easydel/inference/esurge/core/page_pool.py
easydel/inference/esurge/core/sampler.py
easydel/inference/esurge/core/sampling_metadata.py
easydel/inference/esurge/core/single_type_cache_manager.py
easydel/inference/esurge/core/utils.py
easydel/inference/esurge/dashboard.py
easydel/inference/esurge/engine_types.py
easydel/inference/esurge/esurge_engine.py
easydel/inference/esurge/metrics.py
easydel/inference/esurge/monitoring.py
easydel/inference/esurge/multimodal/__init__.py
easydel/inference/esurge/multimodal/cache.py
easydel/inference/esurge/multimodal/manager.py
easydel/inference/esurge/multimodal/types.py
easydel/inference/esurge/outputs.py
easydel/inference/esurge/page_table.py
easydel/inference/esurge/request.py
easydel/inference/esurge/runners/__init__.py
easydel-0.2.0.1.dist-info/WHEEL
easydel-0.2.0.1.dist-info/METADATA
easydel-0.2.0.1.dist-info/RECORD
