Metadata-Version: 2.3
Name: easydel
Version: 0.2.0.1
Summary: Accelerate, Optimize performance with streamlined training and serving options with JAX.
Keywords: Deep Learning,Machine Learning,JAX,CUDA,XLA,Triton,Pallas
Author: Erfan Zare Chavoshi
Author-email: Erfan Zare Chavoshi <Erfanzare810@gmail.com>
License: Apache-2.0
Classifier: Development Status :: 3 - Alpha
Classifier: Intended Audience :: Developers
Classifier: Topic :: Scientific/Engineering :: Artificial Intelligence
Classifier: License :: OSI Approved :: Apache Software License
Classifier: Programming Language :: Python :: 3.11
Classifier: Programming Language :: Python :: 3.12
Classifier: Programming Language :: Python :: 3.13
Requires-Dist: jax>=0.8.2
Requires-Dist: jaxlib>=0.8.2
Requires-Dist: ray[default]==2.51.0
Requires-Dist: eformer==0.0.85
Requires-Dist: ejkernel[triton]==0.0.47
Requires-Dist: einops~=0.8.0
Requires-Dist: transformers~=4.57.3
Requires-Dist: sentencepiece>=0.2.0
Requires-Dist: flax==0.11.2
Requires-Dist: fastapi>=0.115.2
Requires-Dist: wandb>=0.22.2
Requires-Dist: uvloop==0.21.0
Requires-Dist: uvicorn[standard]>=0.32.0
Requires-Dist: jinja2>=3.1.5
Requires-Dist: grain~=0.2.11
Requires-Dist: datasets>=3.6.0
Requires-Dist: gcsfs>=2024.2,<2026
Requires-Dist: zstandard>=0.23.0
Requires-Dist: pyyaml>=6.0
Requires-Dist: msgspec~=0.19.0
Requires-Dist: partial-json-parser>=0.2.1.1.post6
Requires-Dist: google-api-python-client>=2.179.0
Requires-Dist: cryptography>=45.0.6
Requires-Dist: pyzmq>=27.1.0
Requires-Dist: grafanalib>=0.7.1
Requires-Dist: jax[cuda12]>=0.8.2 ; extra == 'gpu'
Requires-Dist: torch==2.8.0 ; extra == 'gpu'
Requires-Dist: tensorboard>=2.19.0 ; extra == 'gpu'
Requires-Dist: ejkernel[gpu]==0.0.47 ; extra == 'gpu'
Requires-Dist: lm-eval~=0.4.9.1 ; extra == 'lm-eval'
Requires-Dist: xprof>=2.20.6 ; extra == 'profile'
Requires-Dist: tb-nightly>=2.21.0a20250820 ; extra == 'profile'
Requires-Dist: xprof-nightly>=2.21.6a20250820 ; extra == 'profile'
Requires-Dist: tensorflow~=2.19.0 ; extra == 'tensorflow'
Requires-Dist: tensorflow-datasets~=4.9.9 ; extra == 'tensorflow'
Requires-Dist: torch==2.8.0 ; extra == 'torch'
Requires-Dist: tensorboard>=2.19.0 ; extra == 'torch'
Requires-Dist: jax[tpu]>=0.8.2 ; extra == 'tpu'
Requires-Dist: tensorboard>=2.19.0 ; extra == 'tpu'
Requires-Dist: ejkernel[tpu]==0.0.47 ; extra == 'tpu'
Requires-Python: >=3.11, <3.14
Project-URL: Documentation, https://easydel.readthedocs.io/en/latest/
Project-URL: Homepage, https://github.com/erfanzar/EasyDeL
Project-URL: Repository, https://github.com/erfanzar/EasyDeL
Provides-Extra: gpu
Provides-Extra: lm-eval
Provides-Extra: profile
Provides-Extra: tensorflow
Provides-Extra: torch
Provides-Extra: tpu
